Metadata-Version: 1.0
Name: dstrb-g-b
Version: 1.3
Summary: Gaussian and Binomial distributions
Home-page: UNKNOWN
Author: ariche Salma
Author-email: UNKNOWN
License: UNKNOWN
Platform: UNKNOWN
